satel_integra_ext/__init__.py
satel_integra_ext/cli.py
satel_integra_ext/playground.py
satel_integra_ext/satel_integra.py
satel_integra_ext-0.4.9.dist-info/AUTHORS.rst
satel_integra_ext-0.4.9.dist-info/LICENSE
satel_integra_ext-0.4.9.dist-info/METADATA
satel_integra_ext-0.4.9.dist-info/WHEEL
satel_integra_ext-0.4.9.dist-info/RECORD
