Metadata-Version: 2.1
Name: satel_integra_ext
Version: 0.4.9
Summary: Communication library and basic testing tool for Satel Integra alarm system.
Home-page: https://github.com/leshqo/satel_integra_ext
License: MIT
Requires-Python: >=3.7,<4.0
Classifier: Development Status :: 2 - Pre-Alpha
Classifier: Intended Audience :: Developers
Classifier: License :: OSI Approved :: MIT License
Classifier: Natural Language :: English
Classifier: Programming Language :: Python :: 3
Classifier: Programming Language :: Python :: 3.7
Classifier: Programming Language :: Python :: 3.8
Classifier: Programming Language :: Python :: 3.9
Classifier: Programming Language :: Python :: 3.10
Classifier: Programming Language :: Python :: 3.11
Classifier: Programming Language :: Python :: 3.12
Provides-Extra: dev
Provides-Extra: test
Requires-Dist: bump2version (>=1.0.1,<2.0.0) ; extra == "dev"
Requires-Dist: click (>=8.1.3,<9.0.0) ; python_version >= "3.8" and python_version < "4.0"
Requires-Dist: cryptography
Requires-Dist: flake8 (>=5.0.4,<6.0.0) ; extra == "test"
Requires-Dist: pytest (>=7.2.0,<8.0.0) ; extra == "test"
Requires-Dist: pytest-cov (>=4.0.0,<5.0.0) ; extra == "test"
Requires-Dist: toml (>=0.10.2,<0.11.0) ; extra == "dev"
Requires-Dist: tox (>=3.27.0,<4.0.0) ; extra == "dev"
Requires-Dist: twine (>=4.0.1,<5.0.0) ; extra == "dev"
